indicnlp/__init__.py
indicnlp/bengali.py
indicnlp-0.0.1.dist-info/LICENSE
indicnlp-0.0.1.dist-info/METADATA
indicnlp-0.0.1.dist-info/WHEEL
indicnlp-0.0.1.dist-info/top_level.txt
indicnlp-0.0.1.dist-info/RECORD
